LICENSE
MANIFEST.in
README.rst
rapydml
setup.py
rapydml.egg-info/PKG-INFO
rapydml.egg-info/SOURCES.txt
rapydml.egg-info/dependency_links.txt
rapydml.egg-info/top_level.txt
rapydml_scripts/__init__.py
rapydml_scripts/compiler.py
rapydml_scripts/html_colors.txt
rapydml_scripts/markuploader.py
rapydml_scripts/util.py
rapydml_scripts/lib/common.pyml
rapydml_scripts/lib/django.pyml
rapydml_scripts/lib/rails.pyml
rapydml_scripts/lib/web2py.pyml
rapydml_scripts/markup/any
rapydml_scripts/markup/html
rapydml_scripts/markup/html5