Metadata-Version: 1.0
Name: rapydml
Version: 0.0.0
Summary: Python-based XML/HTML Compiler
Home-page: http://www.pyjeon.com/
Author: Alexander Tsepkov
Author-email: atsepkov@pyjeon.com
License: GNU GPL3
Platform: any
